README.rst
setup.py
src/piplint/__init__.py
src/piplint.egg-info/PKG-INFO
src/piplint.egg-info/SOURCES.txt
src/piplint.egg-info/dependency_links.txt
src/piplint.egg-info/entry_points.txt
src/piplint.egg-info/top_level.txt