Metadata-Version: 1.0
Name: piplint
Version: 0.2.0
Summary: Checks packages in your active environment against pip requirements files
Home-page: https://github.com/dcramer/piplint
Author: David Cramer
Author-email: dcramer@gmail.com
License: Apache License 2.0
Platform: UNKNOWN
Classifier: Environment :: Console
Classifier: Intended Audience :: Developers
Classifier: Programming Language :: Python
Classifier: Topic :: Software Development
Classifier: Topic :: Utilities
